dictionary_generator/__init__.py
dictionary_generator/__main__.py
dictionary_generator/exercises.py
dictionary_generator/exercises_abs.py
dictionary_generator-1.0.1.dist-info/METADATA
dictionary_generator-1.0.1.dist-info/WHEEL
dictionary_generator-1.0.1.dist-info/entry_points.txt
dictionary_generator-1.0.1.dist-info/top_level.txt
dictionary_generator-1.0.1.dist-info/RECORD
