Metadata-Version: 2.1
Name: dictionary-generator
Version: 1.0.1
Summary: BMSTU word dictionary generator
Home-page: https://github.com/BoldinDmitry/dictionary_bmstu
Author: BMSTU
Author-email: office@bmstu.ru
License: MIT
Platform: UNKNOWN
Classifier: License :: OSI Approved :: MIT License
Classifier: Programming Language :: Python :: 3
Classifier: Programming Language :: Python :: 3.8
Requires-Dist: delta
Requires-Dist: lxml
Requires-Dist: Pillow
Requires-Dist: python-docx
